MANIFEST.in
README.md
setup.py
fake_usrag_bor/__init__.py
fake_usrag_bor/fake_usrag_bor.py
fake_usrag_bor.egg-info/PKG-INFO
fake_usrag_bor.egg-info/SOURCES.txt
fake_usrag_bor.egg-info/dependency_links.txt
fake_usrag_bor.egg-info/not-zip-safe
fake_usrag_bor.egg-info/top_level.txt
fake_usrag_bor/list_of_user_agents/AndroidWebkitBrowser.txt
fake_usrag_bor/list_of_user_agents/Chrome.txt
fake_usrag_bor/list_of_user_agents/Edge.txt
fake_usrag_bor/list_of_user_agents/Firefox.txt
fake_usrag_bor/list_of_user_agents/InternetExplorer.txt
fake_usrag_bor/list_of_user_agents/Opera.txt
fake_usrag_bor/list_of_user_agents/Safari.txt