Metadata-Version: 2.1
Name: fake-usrag-bor
Version: 0.1.3
Summary: Simple package with fake user agents for your requests.
Home-page: https://github.com/oskarmenrus
Author: oskarmenrus
Author-email: oskarmenrus@gmail.com
License: UNKNOWN
Keywords: user,agent,user agent,useragent,fake,fake useragent,fake user agent
Platform: UNKNOWN
Classifier: Programming Language :: Python :: 3
Classifier: License :: OSI Approved :: MIT License
Classifier: Operating System :: OS Independent
